pytest_qt_extras.py
ccsi_foqus-3.27.0.data/scripts/foqus_service.py
ccsi_foqus-3.27.0.dist-info/licenses/LICENSE.md
foqus_lib/__init__.py
foqus_lib/conftest.py
foqus_lib/core.py
foqus_lib/foqus.py
foqus_lib/framework/__init__.py
foqus_lib/framework/at_dict/__init__.py
foqus_lib/framework/at_dict/at_dict.py
foqus_lib/framework/foqusException/__init__.py
foqus_lib/framework/foqusException/foqusException.py
foqus_lib/framework/foqusOptions/__init__.py
foqus_lib/framework/foqusOptions/option.py
foqus_lib/framework/foqusOptions/optionList.py
foqus_lib/framework/gams/HeatInteg.gpr
foqus_lib/framework/gams/HeatIntegration.gms
foqus_lib/framework/gams/__init__.py
foqus_lib/framework/graph/OptGraphOptim.py
foqus_lib/framework/graph/__init__.py
foqus_lib/framework/graph/edge.py
foqus_lib/framework/graph/graph.py
foqus_lib/framework/graph/heatIntegration.py
foqus_lib/framework/graph/node.py
foqus_lib/framework/graph/nodeModelTypes.py
foqus_lib/framework/graph/nodeVars.py
foqus_lib/framework/listen/__init__.py
foqus_lib/framework/listen/listen.py
foqus_lib/framework/ml_ai_models/__init__.py
foqus_lib/framework/ml_ai_models/mlaiSearch.py
foqus_lib/framework/optimizer/BFGS.py
foqus_lib/framework/optimizer/NLopt.py
foqus_lib/framework/optimizer/OptCMA.py
foqus_lib/framework/optimizer/OptSNOBFIT.py
foqus_lib/framework/optimizer/PSUADE.py
foqus_lib/framework/optimizer/SLSQP.py
foqus_lib/framework/optimizer/SM_Optimizer.py
foqus_lib/framework/optimizer/Sample.py
foqus_lib/framework/optimizer/Snobfit.py
foqus_lib/framework/optimizer/__init__.py
foqus_lib/framework/optimizer/optimization.py
foqus_lib/framework/optimizer/problem.py
foqus_lib/framework/optimizer/test/__init__.py
foqus_lib/framework/ouu/OUU.py
foqus_lib/framework/ouu/__init__.py
foqus_lib/framework/plugins/__init__.py
foqus_lib/framework/plugins/pluginSearch.py
foqus_lib/framework/pymodel/__init__.py
foqus_lib/framework/pymodel/heat_integration.py
foqus_lib/framework/pymodel/matlab_fs.py
foqus_lib/framework/pymodel/pymodel.py
ccsi_foqus-3.27.0.dist-info/METADATA
ccsi_foqus-3.27.0.dist-info/WHEEL
ccsi_foqus-3.27.0.dist-info/entry_points.txt
ccsi_foqus-3.27.0.dist-info/top_level.txt
ccsi_foqus-3.27.0.dist-info/RECORD
