Metadata-Version: 2.4
Name: ccsi-foqus
Version: 3.27.0
Summary: FOQUS tool for Simulation based Optimization, Uncertainty Quantification, and Surrogate modeling
Home-page: http://www.acceleratecarboncapture.org/
Author: CCSI FOQUS Team
Author-email: ccsi-support@acceleratecarboncapture.org
Maintainer: CCSI FOQUS Team
Maintainer-email: ccsi-support@acceleratecarboncapture.org
License: BSD 3-Clause Variant (See LICENSE.md details)
License-File: LICENSE.md
Requires-Dist: bokeh!=3.0.*,>=2.4.2
Requires-Dist: boto3
Requires-Dist: cma
Requires-Dist: dask[dataframe,distributed]
Requires-Dist: matplotlib<=3.7.5,>=3.6.0
Requires-Dist: python-tsp==0.3.1
Requires-Dist: mplcursors
Requires-Dist: numpy
Requires-Dist: pandas
Requires-Dist: psutil
Requires-Dist: PyQt5==5.15.10
Requires-Dist: pywin32==306; sys_platform == "win32"
Requires-Dist: requests
Requires-Dist: scipy
Requires-Dist: tqdm
Requires-Dist: TurbineClient>=4.0.3,~=4.0
Requires-Dist: watchtower
Requires-Dist: winshell; sys_platform == "win32"
Requires-Dist: websocket_client>=1.1.0
Dynamic: author
Dynamic: author-email
Dynamic: home-page
Dynamic: license
Dynamic: license-file
Dynamic: maintainer
Dynamic: maintainer-email
Dynamic: requires-dist
Dynamic: summary
